neop/__init__.py
neop/main.py
neop-0.1.0.dist-info/LICENSE
neop-0.1.0.dist-info/METADATA
neop-0.1.0.dist-info/WHEEL
neop-0.1.0.dist-info/top_level.txt
neop-0.1.0.dist-info/RECORD
