Metadata-Version: 2.1
Name: neop
Version: 0.1.0
Summary: Python Package for Predicting Neoantigens and Obtaining Amino Acid Context from MAFs
Home-page: https://github.com/as1000/neop
Author: Ananthan Sadagopan
Author-email: ananthans1000@gmail.com
License: UNKNOWN
Project-URL: Bug Tracker, https://github.com/as1000/neop/issues
Platform: UNKNOWN
Classifier: Programming Language :: Python :: 3
Classifier: License :: OSI Approved :: MIT License
Classifier: Operating System :: OS Independent
Requires-Python: >=3.7
